{"title": "Doch, Migranten vom afrikanischen Kontinent k\u00f6nnen Fl\u00fcchtlinge sein", "subtitle": "Ein Artikel, der behauptet, ein \u201eExperte\u201c habe gesagt, Menschen aus Afrika seien prinzipiell keine Fl\u00fcchtlinge nach der Genfer Konvention, wird in derzeit den sozialen Medien geteilt. Die Aussage geht aus dem Zitat des Wissenschaftlers aber nicht hervor \u2013 und stimmt auch nicht.", "author": "correctiv.org", "date": "2019-07-26T15:39:03+00:00", "vclaim_id": "vclaim-id-25380", "url": "https://correctiv.org/faktencheck/migration/2019/07/26/doch-migranten-vom-afrikanischen-kontinent-koennen-fluechtlinge-sein/", "vclaim": "Falsch. Die \u00dcberschrift des Artikels l\u00e4sst sich aus der Aussage von Kunibert Raffer nicht ableiten. Er hat nicht gesagt, Menschen aus Afrika k\u00f6nnten prinzipiell keine Fl\u00fcchtlinge sein \u2013 und die Behauptung stimmt auch nicht.\n\nEin im Juni 2018 erschienener Artikel des Blogs Halle-Leaks tr\u00e4gt den Titel \u201eExperte: Migranten aus Afrika sind keine Fl\u00fcchtlinge nach Genfer Konvention\u201c. Im zum Artikel geh\u00f6renden Bild hei\u00dft es sogar, \u201emehrere Experten\u201c w\u00fcrden \u201eklarstellen\u201c, dass \u201eAfrika-Migranten\u201c keine Fl\u00fcchtlinge seien. Der aktuell wieder auf Facebook geteilte Artikel besteht aus einem Teaser und einem Zitat von Kunibert Raffer, einem Professor der Universit\u00e4t Wien f\u00fcr Volkswirtschaftslehre im Ruhestand.\n\nIn dem Zitat stuft Raffer einen Teil der vom afrikanischen Kontinent nach Europa kommenden Menschen nicht als Fl\u00fcchtlinge ein. Einen Teil halte er f\u00fcr \u201eMigranten\u201c, deshalb \u201esollte gepr\u00fcft werden\u201c, wer Fl\u00fcchtling im Sinne der Genfer Konvention sei.\n\nDas Zitat ist einem Interview entnommen, das am 28. Juni 2019 auf der Plattform Sputnik-News erschienen war. Auch dieser Artikel tr\u00e4gt einen potenziell irref\u00fchrenden Titel: \u201eMigranten in Europa sind keine Fl\u00fcchtlinge im Sinne der Genfer Konvention \u2013 Experte\u201c. In ihm spricht Raffer sich gegen Seenotrettung aus, da sie \u201eLeute dazu f\u00fchrt, ihr Leben ganz bewusst zu riskieren.\u201c\n\nDas Originalzitat von Raffer lautet: \u201eDas sind Migranten, nicht Fl\u00fcchtlinge im Sinne der Genfer Konvention.\u201c Worauf sich die Aussage urspr\u00fcnglich bezog, ist im Kontext des Artikels jedoch unklar. Auf Nachfrage teilte Raffer nicht mit, worauf er sich in dem Zitat bezog.\n\nDie Aussage der \u00dcberschrift, Menschen aus Afrika seien prinzipiell keine Fl\u00fcchtlinge, l\u00e4sst sich aus dem Zitat also nicht ableiten. Auf Nachfrage verneint Raffer, gesagt zu haben, Menschen vom afrikanischen Kontinent w\u00fcrden prinzipiell nicht unter die Genfer Konvention fallen: \u201eAuch nur zu denken, die Genfer Konvention w\u00fcrde spezifische Regionen ipso facto ausschlie\u00dfen, erscheint mir krank.\u201c Raffers sagt: \u201eDie meisten sogenannten \u2018Fl\u00fcchtlinge\u2019 aus Afrika (\u2026) keine Konventionsfl\u00fcchtlinge \u2013 aber es gibt sicher auch Fl\u00fcchtlinge aus Afrika, die die Kriterien der Konvention erf\u00fcllen.\u201c\n\nArtikel 1 der 1951 verabschiedeten Genfer Fl\u00fcchtlingskonvention definiert einen Fl\u00fcchtling als Person, die \u201caus der begr\u00fcndeten Furcht vor Verfolgung wegen ihrer Rasse, Religion, Nationalit\u00e4t, Zugeh\u00f6rigkeit zu einer bestimmten sozialen Gruppe oder wegen ihrer politischen \u00dcberzeugung sich au\u00dferhalb des Landes befindet, dessen Staatsangeh\u00f6rigkeit sie besitzt, und den Schutz dieses Landes nicht in Anspruch nehmen kann oder wegen dieser Bef\u00fcrchtungen nicht in Anspruch nehmen will (\u2026)\u201c. Ein Migrant hingegen, so der UNHCR, \u201everl\u00e4sst seine Heimat \u00fcblicherweise freiwillig, um seine Lebensbedingungen zu verbessern\u201c.\n\nIn Deutschland wurden zwischen Januar und Juni 2019 laut Angaben des Bundesamts f\u00fcr Migration und Fl\u00fcchtlinge 24.497 Asylantr\u00e4ge auf Basis der Genfer Konvention genehmigt, davon aus Afrika: 1.108 von Menschen aus Eritrea, 894 von Somaliern und 296 von Nigerianern (PDF, S. 3). Ihnen wurde der Status als Fl\u00fcchtlinge nach Paragraf 3 Absatz 1 des Asylgesetzes gew\u00e4hrt, das sich direkt auf die Genfer Konvention bezieht.\n\n\n\n\n\n Unser Ziel ist aufzukl\u00e4ren, wie gezielte Falschmeldungen erkannt und einged\u00e4mmt werden. Wir stellen uns mit Fakten gegen Spaltung und wollen mit unserer Arbeit den Dialog erm\u00f6glichen. Das ist nicht immer leicht \u2013 Hassnachrichten, Beleidigungen und Drohungen geh\u00f6ren zum Alltag unseres Faktencheck-Teams. Aber die Arbeit wirkt: Falschmeldungen werden deutlich weniger geteilt. \n\n\n\n CORRECTIV.Faktencheck ist eine eigenst\u00e4ndige Redaktion innerhalb des gemeinn\u00fctzigen Recherchezentrums. CORRECTIV steht f\u00fcr investigativen Journalismus. Wir bringen systematische Missst\u00e4nde ans Licht und st\u00e4rken eine demokratische und offene Zivilgesellschaft. Leisten Sie einen Beitrag und unterst\u00fctzen Sie uns mit einer Spende! Fakten sind die Grundlage informierter Entscheidungen in unserer Demokratie. Gezielte Desinformation wird genutzt, um unsere Gesellschaft zu spalten, Hass zu verbreiten und damit wom\u00f6glich Gesch\u00e4fte zu machen. Einseitige oder falsche Informationen kreieren verzerrte Weltbilder. Als Teil eines internationalen Netzwerks von Faktenpr\u00fcfern wirkt CORRECTIV.Faktencheck dem entgegen und deckt Falschinformationen und Halbwahrheiten auf.Unser Ziel ist aufzukl\u00e4ren, wie gezielte Falschmeldungen erkannt und einged\u00e4mmt werden. Wir stellen uns mit Fakten gegen Spaltung und wollen mit unserer Arbeit den Dialog erm\u00f6glichen. Das ist nicht immer leicht \u2013Hassnachrichten, Beleidigungen und Drohungen geh\u00f6ren zum Alltag unseres Faktencheck-Teams. Aber die Arbeit wirkt: Falschmeldungen werden deutlich weniger geteilt.CORRECTIV.Faktencheck ist eine eigenst\u00e4ndige Redaktion innerhalb des gemeinn\u00fctzigen Recherchezentrums. CORRECTIV steht f\u00fcr investigativen Journalismus. Wir bringen systematische Missst\u00e4nde ans Licht und st\u00e4rken eine demokratische und offene Zivilgesellschaft. \n\n\n\n Was ist Fake? Was ist Fakt?\n\n Es wird immer wichtiger, zuverl\u00e4ssige Quellen erkennen zu k\u00f6nnen und seri\u00f6se Informationen einzuordnen. Das Programm unserer Online-Akademie richtet sich an Sch\u00fclerinnen und Sch\u00fcler, sowie deren Lehrer. Deutschlandweit werden Journalisten an Schulen vermittelt, um im Unterricht die Medienkompetenz zu st\u00e4rken. Mit Online-Workshops und zugeh\u00f6rigem Unterrichtsmaterial k\u00f6nnen die Themen auch selbstst\u00e4ndig erarbeitet werden. Es wird immer wichtiger, zuverl\u00e4ssige Quellen erkennen zu k\u00f6nnen und seri\u00f6se Informationen einzuordnen. Das Programmunserer Online-Akademie richtet sich an Sch\u00fclerinnen und Sch\u00fcler, sowie deren Lehrer. Deutschlandweit werden Journalisten an Schulen vermittelt, um im Unterricht die Medienkompetenz zu st\u00e4rken. Mit Online-Workshops und zugeh\u00f6rigem Unterrichtsmaterial k\u00f6nnen die Themen auch selbstst\u00e4ndig erarbeitet werden.", "lang": "de"}