{"title": "Ile jest niezamieszka\u0142ych mieszka\u0144 w Polsce?", "subtitle": "Ile jest niezamieszka\u0142ych mieszka\u0144 w Polsce? Sprawdzamy co na ten temat powiedzia\u0142 Andrzej Adamczyk. Czy jego s\u0142owa s\u0105 zgodne z prawd\u0105?", "author": "demagog.org.pl", "date": null, "vclaim_id": "vclaim-id-18664", "url": "https://demagog.org.pl/wypowiedzi/ile-jest-niezamieszkalych-mieszkan-w-polsce/", "vclaim": "Je\u017celi chodzi o penalizacj\u0119 homoseksualizmu, to w Polsce nigdy czego\u015b takiego ni....", "lang": "pl"}