{"title": "Tonel se rompe e causa vazamento de vinho na vin\u00edcola Aurora #boato", "subtitle": "Boato - V\u00eddeo mostra momento em que um tonel na vin\u00edcola Aurora se rompeu e causou um grande vazamento de vinho.", "author": "www.boatos.org", "date": "2019-10-05T15:56:24+00:00", "vclaim_id": "vclaim-id-41051", "url": "https://www.boatos.org/brasil/tonel-rompe-vazamento-vinho-vinicola-aurora.html", "vclaim": "Boato \u2013 V\u00eddeo mostra momento em que um tonel na vin\u00edcola Aurora se rompeu e causou um grande vazamento de vinho.\n\nN\u00e3o sei como \u00e9 hoje em dia (isso denuncia a idade), mas houve um tempo em que dois rituais eram obrigat\u00f3rios em roda de amigos: brindar e dar \u201cum gole para o santo\u201d. E \u00e9 justamente sobre o \u201csegundo ritual\u201d (quase isso) que vamos falar hoje.\n\nDe acordo com mensagens que come\u00e7aram a circular na internet, a vin\u00edcola Aurora (localizada na cidade de Bento Gon\u00e7alves, no Rio Grande do Sul) deu, a contragosto, muitos \u201cgoles para o santo\u201d.\n\nAs imagens mostram o que seria um vazamento de vinho de uma cisterna da empresa. Nas imagens, funcion\u00e1rios tentam, de todas as formas, estancar a sangria. Leia algumas das vers\u00f5es da mensagens que circularam por a\u00ed:\n\nVers\u00e3o 1: Olha o que aconteceu na vin\u00edcola Aurora em Bento Gon\u00e7alves no rio grande do sul. Estourou o tonel de vinho agora a tarde. Vers\u00e3o 2: VIN\u00cdCOLA AURORA, AGORA H\u00c1 POUCO\u2026\n\nMuitos riram da situa\u00e7\u00e3o (que \u00e9 candidata a virar Videocassetada). Outros lamentaram o desperd\u00edcio. S\u00f3 h\u00e1 um detalhe nisso tudo: a hist\u00f3ria nada tem a ver com a vin\u00edcola Aurora e tampouco foi no Brasil. Vamos aos fatos.\n\nDe cara, a mensagem j\u00e1 levantou suspeitas. Afinal, ela tem aquela velha e boa \u201ccara de boato\u201d: vaga, alarmista, com erros de portugu\u00eas e n\u00e3o cita fontes confi\u00e1veis. Para ajudar, ao buscar pelo \u201cacidente na vin\u00edcola Aurora\u201d, nada encontramos.\n\nTentamos ent\u00e3o ir mais a fundo na pesquisa. Foi a\u00ed que descobrimos que o v\u00eddeo n\u00e3o foi gravado no Brasil. Vimos vers\u00f5es em ingl\u00eas e em italiano da mensagem. Ambas s\u00e3o de mais de uma semana (bem antes do v\u00eddeo circular no Brasil) e dizem que o caso ocorreu em uma vin\u00edcola na regi\u00e3o da Sic\u00edlia, na It\u00e1lia (algo que, infelizmente, n\u00e3o conseguimos 100% de confirma\u00e7\u00e3o).\n\nJ\u00e1 sab\u00edamos que o caso n\u00e3o havia ocorrido no Brasil. Mas o tiro de miseric\u00f3rdia na tese foi dada pela pr\u00f3pria vin\u00edcola Aurora. Em um texto no Facebook, a empresa negou que havia ocorrido qualquer acidente e ainda tranquilizou os amantes de vinho. Leia:\n\nDesperd\u00edcio nunca \u00e9 bom, ainda mais se for de vinho. Por isso, pode ficar tranquilo: o v\u00eddeo de um vazamento de vinho n\u00e3o aconteceu na Vin\u00edcola Aurora. Eles est\u00e3o seguros esperando por voc\u00ea! Vin\u00edcola Aurora.\n\nResumindo; a hist\u00f3ria que aponta que um tonel de vinho se rompeu e causou um grande vazamento na vin\u00edcola Aurora \u00e9 falsa. Algu\u00e9m pegou um v\u00eddeo aleat\u00f3rio na internet e saiu compartilhando como se fosse do Brasil. Fim.\n\nPs.: Esse artigo \u00e9 uma sugest\u00e3o de leitores do Boatos.org. Se voc\u00ea quiser sugerir um tema ao Boatos.org, entre em contato com a gente pelo site, Facebook e WhatsApp no telefone (61)99177-9164.", "lang": "pt"}