{"title": "\u00c9 falso que pesquisa americana disse que s\u00f3 6% das v\u00edtimas de Covid-19 morreram pela infec\u00e7\u00e3o | Aos Fatos", "subtitle": "", "author": "www.aosfatos.org", "date": null, "vclaim_id": "vclaim-id-79269", "url": "https://www.aosfatos.org/noticias/e-falso-que-pesquisa-americana-disse-que-so-6-das-vitimas-de-covid-19-morreram-pela-infeccao/", "vclaim": "N\u00e3o \u00e9 verdade que uma pesquisa do CDC (Center for Disease Control, \u00f3rg\u00e3o de sa\u00fade do governo americano) tenha conclu\u00eddo que apenas 6% das v\u00edtimas de Covid-19 nos EUA morreram em decorr\u00eancia da doen\u00e7a, e que a maior parte dos \u00f3bitos foi causada por condi\u00e7\u00f5es preexistentes, como problemas respirat\u00f3rios, cardiovasculares, diabetes e obesidade. Segundo o CDC, a interpreta\u00e7\u00e3o feita pelo jornalista Alexandre Garcia em v\u00eddeo publicado nas redes sociais \u00e9 equivocada, j\u00e1 que 92% dos \u00f3bitos registrados pela infec\u00e7\u00e3o naquele pa\u00eds citam a Covid-19 como a causa b\u00e1sica de morte.\n\nPublicado por Garcia no YouTube, o v\u00eddeo com a falsa alega\u00e7\u00e3o reunia cerca de 1.000 compartilhamentos at\u00e9 a manh\u00e3 desta quarta-feira (2). Publica\u00e7\u00f5es de p\u00e1ginas e perfis bolsonaristas, no entanto, j\u00e1 acumulavam mais de 4.600 compartilhamentos at\u00e9 a mesma data. Todas as postagens foram marcadas com o selo FALSO na ferramenta de monitoramento da rede social (saiba como funciona).\n\nEm v\u00eddeo publicado no dia 31 de agosto, o jornalista Alexandre Garcia cita uma suposta pesquisa americana que teria conclu\u00eddo que apenas 6% das v\u00edtimas de Covid-19 teriam morrido \u201cexclusivamente pelo coronav\u00edrus\u201d. Segundo ele, como os outros \u00f3bitos apresentavam comorbidades, eram pessoas \u201cque j\u00e1 iam morrer\u201d.\n\nO dado ao qual se refere Garcia foi publicado pelo CDC (Center for Disease Control, \u00f3rg\u00e3o do governo americano) no dia 26 de agosto. Segundo o levantamento, que levou em considera\u00e7\u00e3o os 164.280 \u00f3bitos por Covid-19 registrados at\u00e9 aquele momento nos EUA, 6% mencionavam a infec\u00e7\u00e3o como \u00fanica causa da morte. Todas as outras v\u00edtimas possu\u00edam, pelo menos, uma outra causa adicional para a morte, seja doen\u00e7a respirat\u00f3ria, doen\u00e7a cardiovascular ou condi\u00e7\u00f5es como obesidade e diabetes.\n\nEm nota enviada ao Aos Fatos, o CDC explica que a interpreta\u00e7\u00e3o de Garcia \u00e9 incorreta. Segundo a assessoria, \u201cem 92% de todas as mortes que mencionam Covid-19, Covid-19 \u00e9 listado como a causa b\u00e1sica de morte\u201d, ou seja, a condi\u00e7\u00e3o que deu in\u00edcio \u00e0 cadeia de eventos que culminou com a morte da pessoa.\n\nAl\u00e9m disso, a lista de comorbidades inclui condi\u00e7\u00f5es agudas que podem ter ocorrido como resultado da infec\u00e7\u00e3o da Covid-19, como pneumonia, insufici\u00eancia respirat\u00f3ria ou infec\u00e7\u00f5es causadas durante a interna\u00e7\u00e3o no hospital.\n\nDe acordo com o pesquisador do Centro de Biologia Molecular e Engenharia Gen\u00e9tica da Unicamp (Universidade Estadual de Campinas) Marcelo Brand\u00e3o, a alega\u00e7\u00e3o de Garcia \u00e9 uma simplifica\u00e7\u00e3o de an\u00e1lise de dados que distorce os resultados. \u201cA ideia do CDC foi falar o seguinte: dentro desse universo que n\u00f3s estamos olhando, 6% [das mortes] n\u00e3o t\u00eam liga\u00e7\u00e3o com nenhuma outra comorbidade conhecida. Nos outros 94%, existia algum \u00edndice de comorbidade que pode sim estar relacionado \u00e0 doen\u00e7a. A Covid foi uma catalisadora desse \u00f3bito.\u201d\n\nPara explicar a estat\u00edstica, Brand\u00e3o recorre ao exemplo de um acidente a\u00e9reo: se, dentro de um avi\u00e3o est\u00e3o pessoas com doen\u00e7as diversas, como c\u00e2ncer e diabetes em est\u00e1gio avan\u00e7ado, n\u00e3o se pode dizer que a pessoa morreu por conta da condi\u00e7\u00e3o pr\u00e9via de sa\u00fade caso ocorra um acidente e a aeronave caia. \u201cAquele paciente, por exemplo, com c\u00e2ncer terminal que estava sendo transportado de um hospital para o outro para tentar uma \u00faltima cirurgia, morreu porque estava com c\u00e2ncer ou morreu por conta da queda do avi\u00e3o?\u201d\n\nOutro ind\u00edcio que vai contra a interpreta\u00e7\u00e3o de Garcia \u00e9 que o pr\u00f3prio levantamento do CDC traz uma visualiza\u00e7\u00e3o com o excesso de mortes durante a pandemia de Covid-19. O \u00f3rg\u00e3o estimava, de 1\u00ba de janeiro a 26 de maio, entre 183.393 a 245.305 mortes em excesso. Esse dado \u00e9 calculado com base no n\u00famero de mortes registradas por ano ao longo de uma s\u00e9rie hist\u00f3rica. Quando o n\u00famero ultrapassa as estimativas previstas, as mortes s\u00e3o contabilizadas como excedentes.\n\nDesinforma\u00e7\u00e3o nos EUA. A mesma interpreta\u00e7\u00e3o incorreta foi publicada pelo presidente dos EUA, Donald Trump, no dia 29 de agosto. O l\u00edder americano retuitou uma publica\u00e7\u00e3o de um apoiador que dizia que apenas 6% das mortes registradas como Covid-19 haviam sido decorrentes da doen\u00e7a e que todas as demais foram causadas por \u201coutras doen\u00e7as s\u00e9rias\u201d. O Twitter deletou as publica\u00e7\u00f5es no mesmo dia, alegando que elas violavam as regras da rede social.\n\nA informa\u00e7\u00e3o falsa foi tamb\u00e9m desmentida por equipes de jornais estrangeiros, como os canais WBRC, WTHR e CBS e tamb\u00e9m pela ag\u00eancia de checagem americana Factcheck.org.\n\nOutro lado. Na tarde da \u00faltima ter\u00e7a-feira (1\u00ba), Aos Fatos entrou em contato com a assessoria de comunica\u00e7\u00e3o de Alexandre Garcia pelo telefone e foi orientado a enviar um e-mail que apontasse as informa\u00e7\u00f5es falsas divulgadas no v\u00eddeo. At\u00e9 a publica\u00e7\u00e3o desta checagem, no entanto, n\u00e3o houve retorno do jornalista sobre o caso.\n\nDe acordo com nossos esfor\u00e7os para alcan\u00e7ar mais pessoas com informa\u00e7\u00e3o verificada, Aos Fatos libera esta reportagem para livre republica\u00e7\u00e3o com atribui\u00e7\u00e3o de cr\u00e9dito e link para este site.", "lang": "pt"}