{"title": "Still wrong: malaria doesn\u2019t kill a child every 30 seconds in Africa", "subtitle": "An", "author": "africacheck.org", "date": null, "vclaim_id": "vclaim-id-28914", "url": "https://africacheck.org/spot-check/still-wrong-malaria-doesnt-kill-a-child-every-30-seconds-in-africa/", "vclaim": "about the number of child deaths in Africa from malaria has surfaced again.\n\n\u201cAccording to Unicef, malaria kills one child every 30 seconds in Africa,\u201d\n\nrticle, which was reporting on the rollout of a malaria vaccine pilot programme in Ghana, said that this meant \u201cabout 3,000\u201d children died from malaria every day.\n\nDoes the latest data support this worrying claim?\n\nThe statistic cited in the news report can be found on the United Nations Children's Fund (Unicef) website. But the webpage is dated\n\nIn order for the claim to be correct, just over one million children would have to die from malaria in Africa. The most recent data does not show this.\n\npeople died from malaria globally. This means a person died every 1 minute and 12 seconds.\n\nThe majority of these deaths were in the Africa region, where an estimated\n\npeople died. This means a person died every 1 minute and 18 seconds - or 1,104 people every day. (\n\nThe WHO provides a\n\nof malaria deaths for children under the age of five.\n\n\u201cMost of the deaths under five occur in the WHO Africa region,\u201d Collins\n\nchildren under the age of five died from the disease in the Africa region.\n\nThat means that 704 children under five died every day - or one child every two minutes. (\n\nThe claim that \u201cmalaria kills one child every 30 seconds in Africa\u201d is therefore not supported by the best available data.", "lang": "en"}