{"title": "Nein, diese Pflastersteine wurden nicht f\u00fcr Anti-Rassismus-Demos bereitgelegt", "subtitle": "Anhand von Baustellen-Fotos wird behauptet, Steine seien f\u00fcr die \u201eAntifa\u201c bereitgelegt worden, mit Genehmigung der Beh\u00f6rden. Das ist falsch.", "author": "correctiv.org", "date": "2020-06-10T15:43:22+00:00", "vclaim_id": "vclaim-id-45735", "url": "https://correctiv.org/faktencheck/2020/06/10/nein-diese-fotos-zeigen-keine-pflastersteine-die-fuer-anti-rassismus-demonstrationen-bereitgelegt-wurden/", "vclaim": "Falsch. In allen F\u00e4llen handelt es sich laut Polizei und St\u00e4dten um regul\u00e4re Baustellen. In keinem Fall ist den Beh\u00f6rden das Bereitlegen von Steinen bekannt, meist verliefen die Demonstrationen friedlich.\n\nIn einem Youtube-Video vom 5. Juni warnt eine M\u00e4nnerstimme: \u201eDie deutsche Antifa und die deutsche Black Lives Matter Bewegung hat f\u00fcr morgen [\u2026] zu zahlreichen Protesten nach US-amerikanischem Vorbild in deutschen St\u00e4dten aufgerufen.\u201c In den USA seien die Proteste von Radikalen unterwandert worden, behauptet der Sprecher. \u201eNormalerweise sollte uns die Polizei vor solchen Szenen sch\u00fctzen und Schadensbegrenzung betreiben, stattdessen wurden mir heute diese Bilder \u00fcber Telegram zugeschickt\u201c. Die darauf folgenden Bilder zeigen Baustellen mit freiliegenden Pflastersteinen in mehreren deutschen St\u00e4dten.\n\nDer Sprecher deutet damit an, deutsche Beh\u00f6rden und die Polizei w\u00fcrden die Bereitstellung von Pflastersteinen f\u00fcr Demonstranten unterst\u00fctzen. Das Youtube-Video wurde mittlerweile gel\u00f6scht. Kurz vor der L\u00f6schung hatte es 189.000 Aufrufe. Auf mehreren anderen Youtube-Kan\u00e4len ist es weiter zu sehen.\n\nAuch auf Facebook wird die Falschmeldung verbreitet\n\nAuch in einem Facebook-Beitrag vom 5. Juni sind die Bilder von Baustellen zu sehen, zusammen mit der Behauptung: \u201eDamit schmei\u00dfen sie morgen die Gesch\u00e4fte kaputt. Das Ganze wird weltweit von den Demokraten / radikalen Linken koordiniert und wurde von unserer korrupten Regierung abgesegnet. Sie wollen den gleichen Chaos wie in den USA weltweit erzeugen, weil sie wieder die Kontrolle haben wollen!\u201c Der Beitrag wurde mehr als 500 Mal geteilt.\n\nFalschmeldungen aus den USA sollen in Deutschland reproduziert werden\n\nDie Beitr\u00e4ge in Sozialen Netzwerken beziehen sich auf die Demonstrationen in zahlreichen deutschen St\u00e4dten gegen Rassismus am Wochenende des 6. und 7. Juni. Die Fotos sind offenbar der Versuch, ein in den USA kursierendes Narrativ in Deutschland zu reproduzieren. Dort gibt es anhaltende Proteste nach dem gewaltsamen Tod des Schwarzen George Floyd bei seiner Festnahme durch Polizisten am 25. Mai. In diesem Kontext tauchten in den USA Behauptungen auf, in gezielten Aktionen w\u00fcrden von linken Extremisten und Polizisten Paletten mit Ziegelsteinen in der N\u00e4he der Proteste bereitgestellt. Diese Theorie verbreitete unter anderem die f\u00fcr irref\u00fchrende Meldungen bekannte Webseite Law Enforcement Today, die sich wiederum auf die Webseite Breitbart bezog.\n\nFaktenchecker von Politifact haben die Behauptungen gepr\u00fcft und kommen zu dem Schluss, dass sie gr\u00f6\u00dftenteils falsch sind. Auch ein Verifikationsteam des Senders NBC untersuchte die Vorw\u00fcrfe in mehreren St\u00e4dten und widerlegte sie. Teilweise handelte es sich nach den Recherchen der Journalisten um normale, bereits bestehende Baustellen, teilweise lagen diese gar nicht in der N\u00e4he von Protestrouten.\n\nDas Wei\u00dfe Haus ver\u00f6ffentlichte laut US-amerikanischen Journalisten ebenfalls auf Twitter ein Video mit der Behauptung, Fotos w\u00fcrden zeigen, wie die \u201eAntifa\u201c Paletten mit Ziegelsteinen f\u00fcr Protestierende bereitstelle. Nach Hinweisen von Journalisten, dass diese Behauptungen schon widerlegt wurden, l\u00f6schte das Wei\u00dfe Haus das Video laut Medienberichten kommentarlos.\n\nWas steckt hinter den Behauptungen in Deutschland?\n\nBilder aus neun deutschen St\u00e4dten werden bei Facebook und Youtube im Kontext dieses falschen Narrativs geteilt. Unter anderem verbreitete au\u00dferdem die AfD Hannover einige dieser Fotos auf Twitter weiter. Wir haben alle gepr\u00fcft.\n\n1. Behauptungen zu Pflastersteinen in Mainz: Stadt und Polizei dementieren\n\nIn dem Youtube-Video und in dem Facebook-Beitrag wird ein Bild vor dem Mainzer Hauptbahnhof gezeigt, das angeblich belegen soll, dass am 5. Juni eigens f\u00fcr die Demonstrationen Pflastersteine bereit gelegt wurden. Tats\u00e4chlich handelt es sich jedoch um eine regul\u00e4re Baustelle, die schon l\u00e4nger besteht.\n\nAuf eine Presseanfrage von CORRECTIV schrieb die Stadt Mainz: \u201eDie Bilder der Baustelle am Hauptbahnhof Mainz sind real, diese ist seit Mitte Mai eingerichtet, da Kabel neu verlegt werden f\u00fcr das Aufstellen einer Anzeigetafel der \u2018Mainzer Mobilit\u00e4t\u2019.\u201c Vergleichbare Anzeigen f\u00e4nden sich bereits in der N\u00e4he vor Ort. \u201eDie Pflastersteine der Baustelle waren am Wochenende in dicke Planen eingewickelt, also nicht sichtbar. Bei der Demonstration gegen Rassismus \u2013 Veranstaltungsort etwa 2 km vom Bahnhof entfernt am Mainzer Rheinufer \u2013 waren circa 2.500 Personen. Der Protest verlief durchweg friedlich. Von Pflastersteinen, die vermeintlich geworfen wurden, ist nichts bekannt.\u201c\n\nDie Polizei Mainz best\u00e4tigte diese Angaben gegen\u00fcber CORRECTIV: \u201eDie Baustelle steht in keinem Zusammenhang zu irgendwelchen Demonstrationen. Es wurden im Zusammenhang mit der Anti-Rassismus-Demonstration in Mainz keinerlei St\u00f6rer geschweige denn Pflastersteine festgestellt.\u201c\n\nIn dem Youtube-Video und bei Facebook werden auch Fotos der K\u00f6lner Schildergasse als vermeintliche Belege f\u00fcr das Narrativ verbreitet.\n\nDie Polizei K\u00f6ln antworte auf eine CORRECTIV-Anfrage am 9. Juni: \u201eDer Polizei K\u00f6ln liegen keine Informationen dar\u00fcber vor, dass am vergangenen Wochenende bei Demonstrationen in K\u00f6ln und Leverkusen Pflastersteine geworfen wurden.\u201c\n\nDie Pressestelle der Stadt K\u00f6ln best\u00e4tigte auf Nachfrage telefonisch am 9. Juni 2020: \u201eDas ist eine ganz normale, regul\u00e4re Baustelle\u201c.\n\nIm Zusammenhang mit dem Narrativ der bereitgestellten Pflastersteine wird auch ein Bild vor dem hessischen Landtag in Wiesbaden bei Facebook verbreitet.\n\nDas f\u00fcr Wiesbaden zust\u00e4ndige Polizeipr\u00e4sidium Westhessen stellt auf Nachfrage von CORRECTIV klar: \u201eDie von Ihnen angesprochene Behauptung entspricht nicht den Tatsachen. Das im Internet kursierende und von Ihnen angeh\u00e4ngte Bild zeigt eine Baustelle vor dem Hessischen Landtag auf dem Wiesbadener Schlossplatz. In dem umz\u00e4unten Baustellenbereich finden bereits seit mehreren Wochen Erdarbeiten statt und die hierbei herausgerissenen Pflastersteine werden seitdem in den zu sehenden Kisten gelagert.\u201c Die Baustelle auf dem Wiesbadener Schlossplatz befinde sich \u00fcber einen Kilometer Luftlinie vom Luisenplatz, dem Ort der Versammlung, entfernt.\n\nIn einer Pressemitteilung vom 6. Juni bezeichnete die Polizei die Versammlung auf dem Luisenplatz in Wiesbaden anl\u00e4sslich des bundesweiten Aktionstages zum Thema \u201eBlack Live Matters\u201c als \u201est\u00f6rungsfrei\u201c.\n\nDie Stadt Wiesbaden verwies auf Nachfrage von CORRECTIV auf eine Pressemitteilung, die sie bereits am 20. Februar ver\u00f6ffentlichte und in der sie \u00fcber den Ausbau des Fernw\u00e4rmenetzes und damit verbundenen Bauarbeiten informierte. In dem dort verlinkten Plan der Bauabschnitte ist deutlich markiert, dass auch vor dem Landtag Arbeiten stattfinden werden.\n\n\n\n Wir informieren Sie alle zwei Wochen \u00fcber unsere interessantesten Faktenchecks und Hintergrundberichte \u00fcber Desinformation. \n\n\n\n Faktenchecks per MailWir informieren Sie alle zwei Wochen \u00fcber unsere interessantesten Faktenchecks und Hintergrundberichte \u00fcber Desinformation.\n\n4. Behauptungen zu Pflastersteinen in Karlsruhe: Stadt und Polizei dementieren\n\nAuch ein Foto aus Karlsruhe wird im Zusammenhang mit dem Pflasterstein-Narrativ bei Facebook und Youtube verbreitet. In dem Facebook-Beitrag vom 5. Juni steht unter anderem: \u201eAm Donnerstag wurde diese \u2018Baustelle\u2019 errichtet.\u201c Mit den Anf\u00fchrungszeichen wird suggeriert, es handele es sich um keine richtige Baustelle, sondern nur eine Tarnung f\u00fcr die bereit gelegten Steine f\u00fcr Demonstranten. Das ist falsch.\n\nAuf eine Presseanfrage von CORRECTIV antwortete die Pressestelle der Stadt Karlsruhe: \u201eDie Fotos zeigen eine eine echte Baustelle (Kabelverlegungsarbeiten der Telekom) in der Karlsruher Innenstadt mit nat\u00fcrlich v\u00f6llig falscher Kommentierung. Genehmigt sind die Baut\u00e4tigkeiten an dieser Stelle durch das Ordnungsamt der Stadt Karlsruhe bis einschlie\u00dflich 12. Juni 2020.\u201c Weiter schrieb die Stadt: \u201eEs gab keinerlei Vorkommnisse mit Pflastersteinen bei den Versammlungen am Wochenende. Im Gegenteil: Insgesamt 4.500 Menschen demonstrierten friedlich auf zwei Versammlungen im Stadtgebiet gegen Rassismus.\u201c\n\nDas Polizeipr\u00e4sidium Karlsruhe best\u00e4tigte gegen\u00fcber CORRECTIV: \u201eDie Versammlungen am Wochenende in Karlsruhe verliefen ohne Probleme (von zum Teil unzureichenden Abst\u00e4nden abgesehen). Erkenntnisse, dass von Seiten der Versammlungsteilnehmer Steine bereitgelegt wurden, gibt es beim Polizeipr\u00e4sidium Karlsruhe nicht.\u201c\n\n5. Stadt Marburg: Kein Einsatz von Steinen bei Demos\n\nIn einem weiteren Facebook-Beitrag wird auch ein Foto aus Marburg mit S\u00e4cken voll Steinen als vermeintliche Belege f\u00fcr das Narrativ verbreitet.\n\nAuf eine Presseanfrage von CORRECTIV schrieb die Stadt Marburg dazu: \u201eDie S\u00e4cke mit den Pflastersteinen geh\u00f6ren zu der Baustelle am Rudolphsplatz, wo der Verbindungsweg von der Weidenh\u00e4user Br\u00fccke zur Bushaltestelle Rudolphsplatz hergestellt wird. Die S\u00e4cke stehen aktuell noch dort, weil sie noch nicht verbaut werden konnten.\u201c Au\u00dferdem stellt die Stadt klar: \u201eBei der Demonstration gegen rassistisch motivierte Gewalt am Samstag, 6. Juni, in Marburg kam es nicht zum Einsatz von Pflastersteinen durch Demonstrierende. Es liegen auch keine Erkenntnisse vor, dass Demonstrierende gezielt im Vorfeld Steine bereitgelegt haben.\u201c\n\n6. Stadt Erfurt: Es gab gar keine Demo am Wochenende\n\nIn dem verbreiteten Youtube-Video vom 5. Juni wird auch ein Foto aus Erfurt als vermeintlicher Beleg f\u00fcr bereitgelegte Pflastersteine genutzt.\n\nDie Pressestelle der Stadt Erfurt antwortete auf unsere Presseanfrage: \u201eZu sehen ist hier eine Lagerfl\u00e4che der Firma Strassing. Diese Firma baut aktuell am Benediktsplatz, der sich rund 500 Meter entfernt inmitten der historischen Altstadt befindet. Hier ist es r\u00e4umlich sehr eng. Deshalb hat die Firma Strassing auf dem Domplatz eine Lagerfl\u00e4che beantragt und genehmigt bekommen.\u201c\n\nDie Landespolizeiinspektion Erfurt antwortete auf unsere Presseanfrage, ob Pflastersteine bei Demonstrationen am 6. und 7. Juni genutzt wurden: \u201eIn Erfurt haben keine Demonstrationen stattgefunden, somit ist die Frage hinf\u00e4llig.\u201c\n\nAuch ein Bild aus D\u00fcsseldorf wird von den Urhebern des Youtube-Videos als angeblicher Beweis f\u00fcr das Narrativ genutzt.\n\nAuf eine Presseanfrage von CORRECTIV schickte die Pressestelle der Stadt D\u00fcsseldorf ein Bild der Baustelle: \u201eWie Sie sehen, ist das eine ganz normale Leitungsbaustelle. [\u2026] Als Landeshauptstadt D\u00fcsseldorf verwahren wir uns gegen die Unterstellung, wir h\u00e4tten in irgendeiner Form Beihilfe zu geplanten Gewalttaten geleistet.\u201c\n\nDas Polizeipr\u00e4sidium D\u00fcsseldorf antwortete auf unsere Fragen, ob die Behauptungen in dem Youtube-Video zu den Pflastersteinen korrekt seien, und ob es bei den Anti-Rassismus-Demonstrationen am Wochenende des 6. und 7. Juni in D\u00fcsseldorf zum Einsatz von Pflastersteinen durch Demonstranten gekommen sei: \u201eIhre beiden Fragen k\u00f6nnen wir mit einem knappen \u2018Nein\u2019 beantworten.\u201c\n\nCORRECTIV ist spendenfinanziert\n\n Wir recherchieren zu Missst\u00e4nden in der Gesellschaft, bieten Bildungsprogramme an und setzen uns f\u00fcr Informationsrechte und Pressefreiheit ein.\n\n Unterst\u00fctzen Sie uns dabei\n\n8. Hamburg: Baustelle besteht schon seit Ende 2019\n\nAuch Fotos von Steinen am Hamburger Jungfernstieg werden in dem Youtube-Video und in dem Facebook-Beitrag verbreitet.\n\nAuf unsere Presseanfrage antwortete die Polizei Hamburg am 9. Juni: \u201eBei dem gezeigten Ausschnitt mit Hamburg-Bezug handelt es sich um die Baustelleneinrichtungsfl\u00e4che Ballindamm, zwischen Bergstra\u00dfe und Alstertor auf der Wasserseite. Dort finden seit Ende letzten Jahres umfangreiche Stra\u00dfenbauarbeiten im Zusammenhang mit dem Ausbau der Velorouten 5 und 6 unter Federf\u00fchrung des Bezirksamtes Mitte statt. In der Baustelleneinrichtungsfl\u00e4che wird Baumaterial gelagert.\u201c\n\nDie Baustelle ist demnach nicht erst seit kurzem und nicht eigens f\u00fcr die Demonstrationen errichtet worden.\n\nWeiter verwies die Polizei Hamburg auf eine Pressemitteilung vom 7. Juni, derzufolge Einsatzkr\u00e4fte am Rande der friedlichen Demonstration mit Pyrotechnik, Flaschen und Steinen beworfen worden seien. \u201eUns liegen keine Hinweise darauf vor, dass dieses Bewurfmaterial gezielt bereit gelegt wurde.\u201c\n\nDie in dem Youtube-Video und dem Facebook-Beitrag gezeigte Baustelle besteht also bereits seit Ende 2019. Laut Polizei gibt es keine Hinweise, dass Steine gezielt bereit gelegt wurden. Polizisten seien jedoch mit Steinen angegriffen worden.\n\nAuch Aufnahmen aus Berlin tauchen in dem Youtube-Video und bei Facebook auf. Zu sehen ist eine Baustelle am Bahnhof Potsdamer Platz. Auf Nachfrage von CORRECTIV antwortete das Bezirksamt Mitte: \u201eDie Baustelle [\u2026] wurde deutlich vor den Protesten (vor Corona) eingerichtet. Sie ist weiterhin aktuell. Mit Sicherheit k\u00f6nnen wir sagen, dass im Bezirksamt Mitte keine Baustellen f\u00fcr Proteste eingerichtet werden. Baustellen gibt es nat\u00fcrlich im Bezirk und in der ganzen Stadt. Diese werden nicht in Vorbereitung auf Demonstrationen ber\u00e4umt.\u201c\n\nDie Polizei Berlin antwortete auf unsere Anfrage: \u201eDie Polizei Berlin legte oder legt weder Pflastersteine bereit, noch unterst\u00fctzt oder deckt sie derartige Unternehmungen!\u201c", "lang": "de"}