{"title": "Taiana: \u201cLos fondos para vivienda de 2013 alcanzaron s\u00f3lo el 3,07% del total del presupuesto general\u201d", "subtitle": "<img class=\" size-full wp-image-3579\" src=\"http://new.chequeado.com/wp-content/uploads/2013/10/taiana.jpg\" width=\"490\" height=\"220\" /><br /><br /><span cla", "author": "chequeado.com", "date": null, "vclaim_id": "vclaim-id-404", "url": "https://chequeado.com/ultimas-noticias/taiana-los-fondos-para-vivienda-de-2013-alcanzaron-solo-el-307-del-total-del-presupuesto-general/", "vclaim": "Durante una , el primer candidato a legislador porte\u00f1o por el Frente para la Victoria (FpV), Jorge Taiana, destac\u00f3 la ausencia de una pol\u00edtica habitacional del gobierno de Mauricio Macri, y argument\u00f3: \u201cLos fondos para programas de vivienda de 2013 alcanzaron s\u00f3lo el 3,07% del total del presupuesto general\u201d. La fuente que utiliz\u00f3 el candidato fue un informe del sitio La F\u00e1brica Porte\u00f1a, que conduce el ministro de Trabajo de la Naci\u00f3n, Carlos Tomada.\n\nLa afirmaci\u00f3n de Taiana coincide con los datos oficiales disponibles. El porcentaje para 2012 coincide con su frase, pero el de 2013 es m\u00e1s bajo que el mencionado y viene descendiendo desde 2011, adem\u00e1s de que si se considera el presupuesto devengado la ejecuci\u00f3n es menor en todos los a\u00f1os desde 2008.\n\nSeg\u00fan un de la Asociaci\u00f3n por la Igualdad y la Justicia (ACIJ), los fondos destinados a la construcci\u00f3n de viviendas, calculados como porcentaje del presupuesto original aprobado por la Legislatura, muestran una tendencia negativa en el per\u00edodo 2008-2013. El presupuesto para Vivienda representa actualmente el 2,7% del presupuesto original, mientras que en 2008 era del 3,7 por ciento. En 2012, el porcentaje fue del 3,1 por ciento.\n\nLos datos surgen de las leyes de Presupuesto publicadas por el Gobierno de la Ciudad en el Bolet\u00edn Oficial (ver ).\n\nGastos totales del GCBA destinados a Vivienda. Porcentaje del presupuesto original (en $ corrientes). \n\n\n\n* No comprende la ampliaci\u00f3n presupuestaria realizada por la Ley 4219.\n\nSi se calcula el presupuesto de Vivienda que efectivamente se ejecut\u00f3, en todos los a\u00f1os del per\u00edodo los gastos devengados representaron porcentajes menores a los asignadas originalmente por la Legislatura. Las cifras fueron deflactadas por la ACIJ en base al IPC-7 Provincias del Centro de Estudios para el Desarrollo Argentina (CENDA).\n\nGastos totales del GCBA destinados a Vivienda. Porcentaje del presupuesto original y el devengado (en $ constantes).\n\n\n\n* No se presentan datos de cr\u00e9dito devengado en 2012 porque el informe se public\u00f3 antes de que se publicara la informaci\u00f3n de todo el a\u00f1o pasado.\n\n\n\nPor otro lado, para la Asociaci\u00f3n Argentina de Presupuesto y Administraci\u00f3n Financiera P\u00fablica (ASAP), el presupuesto de Vivienda es el que menos ejecuci\u00f3n registra en la Ciudad. \u201cLa funci\u00f3n Vivienda contin\u00faa siendo la de mayor subejecuci\u00f3n de la Administraci\u00f3n Central (33,9%), pese a que su nivel de ejecuci\u00f3n ha aumentado sensiblemente de 2012 a este a\u00f1o\u201d, se\u00f1ala en su del segundo trimestre de 2013.\n\nEntre 2001 y 2008, la Ciudad de Buenos Aires en estado de emergencia habitacional por el Poder Legislativo porte\u00f1o. En 2008, la Legislatura aprob\u00f3 la , que extendi\u00f3 el plazo hasta 2010 y obligaba al Poder Ejecutivo a presentar un plan para subsanar el d\u00e9ficit de viviendas, pero en febrero de 2009 esa ley por Macri.\n\nEl informe elaborado para la ACIJ por los investigadores Mar\u00eda Trevisani Vespa y Juan Mamberti subraya que \u201cla situaci\u00f3n cr\u00edtica habitacional se mantiene en toda su profundidad, a pesar de que la Ciudad atraviesa un momento de expansi\u00f3n y recuperaci\u00f3n econ\u00f3mica\u201d.\n\nEl Centro de Estudios para el Desarrollo Econ\u00f3mico Metropolitano (CEDEM) de la Ciudad inform\u00f3 en un publicado en enero de 2012: \u201cSe verific\u00f3 un ininterrumpido crecimiento de la superficie solicitada para construir en la Ciudad, que estuvo motorizado fundamentalmente por la edificaci\u00f3n de viviendas de primera categor\u00eda, orientadas a sectores de altos ingresos, que generalmente no necesitan el acceso al cr\u00e9dito para la adquisici\u00f3n de inmuebles\u201d.\n\nEl organismo que depende de la Direcci\u00f3n General de Estad\u00edstica y Censos (DGEyC) agreg\u00f3 que la inversi\u00f3n \u201cestuvo concentrada en muy pocos barrios de la Ciudad (\u2026), entre los que se destaca Palermo, Caballito, Villa Urquiza y Puerto Madero. En cambio, barrios vinculados a sectores de menores ingresos, como los del sur de la Ciudad, tuvieron muy escaso dinamismo, manteni\u00e9ndose al margen de este boom\u201d.\n\nRa\u00fal Fern\u00e1ndez Wagner, arquitecto especialista en Tecnolog\u00eda de la Vivienda y profesor del \u00c1rea de Urbanismo del Instituto del Conurbano de la Universidad Nacional de General Sarmiento (ICO-UNGS), explic\u00f3 a Chequeado.com que el alto crecimiento gener\u00f3 un gran desarrollo del mercado y, por lo tanto, un incesante alza de los precios del suelo, adem\u00e1s de la especulaci\u00f3n inmobiliaria.\n\n\u201cEl d\u00e9ficit de 140.000 hogares y las 341.000 viviendas vac\u00edas reflejan la injusta distribuci\u00f3n espacial de la ciudad de Buenos Aires\u201d, concluy\u00f3 el especialista, respecto de los datos que se pueden encontrar en un elaborado por el Instituto de Vivienda de la Ciudad y la del Censo 2010 para la Ciudad de Buenos Aires.\n\nLos datos surgen de los res\u00famenes del Presupuesto publicados por el Ministerio de Hacienda de la Ciudad (ver c\u00e1lculos).", "lang": "es"}