{"title": "#Spots Stolbizer: \u201cLa Argentina que queremos\u201d", "subtitle": "La precandidata del espacio Progresistas apunta a valores como el esfuerzo y la decencia, pero no enuncia en sus spots frases contrastables con hechos y da", "author": "chequeado.com", "date": null, "vclaim_id": "vclaim-id-5195", "url": "https://chequeado.com/ultimas-noticias/stolbizer-la-argentina-que-queremos/", "vclaim": "La precandidata del espacio Progresistas apunta a valores como el esfuerzo y la decencia, pero no enuncia en sus spots frases contrastables con hechos y datos, o propuestas.\n\nMargarita Stolbizer (GEN) se presenta como precandidata a Presidenta por el frente Progresistas, y como parte de su campa\u00f1a difundi\u00f3 spots centrados en valores \u00e9ticos y morales como el trabajo, el esfuerzo, la educaci\u00f3n y la decencia. Pese a esto, ninguno contiene frases contrastables con hechos y datos o propuestas a llevar a cabo en caso de llegar al Gobierno.\n\n\u201cLa Argentina que queremos\u201d es el t\u00edtulo de la campa\u00f1a y el pie con el que parten todos los spots. En las piezas se alude desde los valores \u00e9ticos y morales a temas como la educaci\u00f3n (\u201clos que mandamos a nuestros hijos a la escuela para que sean mejores personas\u201d), la decencia (\u201cyo quiero una Argentina decente, donde los que gobiernen no roben\u201d), el esfuerzo o el respeto. Stolbizer se encarga de la conclusi\u00f3n con el slogan \u201cvot\u00e1 con la cabeza, y con el coraz\u00f3n\u201d.\n\nEn ninguno de los spots hay frases chequeables con hechos y datos, o propuestas a llevar a cabo durante la gesti\u00f3n. Tampoco en los cortos difundidos que critican al gobernador bonaerense y precandidato presidencial del FPV, Daniel Scioli, y al jefe de Gobierno porte\u00f1o y precandidato presidencial del PRO, Mauricio Macri, y apuntan a que el elector no se \u201ctrague un sapo\u201d.\n\nEl espacio Progresistas, pese a esto, s\u00ed tiene otros materiales audiovisuales con datos y propuestas en el canal oficial de YouTube de la precandidata; al igual que en su sitio web, donde presentae distintos \u201ccompromisos\u201d de acci\u00f3n (\u201ccon el campo\u201d, \u201ccon los derechos humanos\u201d, \u201ccon la universidad p\u00fablica\u201d).\n\nHay que recordar que un spot es un recurso de campa\u00f1a pol\u00edtica que busca atraer al electorado de distintas maneras. Como sostiene Mario Riorda, doctor en Comunicaci\u00f3n Social y especialista en Comunicaci\u00f3n Pol\u00edtica, los spots tienen tres funciones: proporcionar informaci\u00f3n, movilizar al electorado estimulando su inter\u00e9s en los comicios y persuadir al electorado, mostrando que determinado partido es el m\u00e1s apropiado para conducir el pa\u00eds.\n\nEs decir que no necesariamente deben contener datos chequeables.\u201cHay spots que trabajan sobre proposiciones o ideas generales, preferentemente abstractas, breves, centradas en valores y con mensajes que traten temas amplios que, en general, gozan de mayoritaria aceptaci\u00f3n\u201d, concluy\u00f3 el especialista.\n\nChequeado analizar\u00e1 los spots de los precandidatos a Presidente y se\u00f1alar\u00e1, como en este caso, cuando se trate de un aviso que no puede ser contrastado con datos y hechos.\n\nEn la recopilaci\u00f3n de spots participaron Catalina Ceparro, Sofia Kowal y Camila Giacchino.", "lang": "es"}